formerbox/__init__.py
formerbox/__main__.py
formerbox/cli/__init__.py
formerbox/cli/convert_dataset.py
formerbox/cli/functional/__init__.py
formerbox/cli/functional/preprocess.py
formerbox/cli/preprocess.py
formerbox/cli/subcommand.py
formerbox/cli/train.py
formerbox/cli/train_tokenizer.py
formerbox/common/__init__.py
formerbox/common/dataclass_argparse.py
formerbox/common/from_partial.py
formerbox/common/has_params.py
formerbox/common/registrable.py
formerbox/common/utils.py
formerbox/contrib/__init__.py
formerbox/contrib/datasets/__init__.py
formerbox/contrib/datasets/jsonlines.py
formerbox/contrib/lightning/__init__.py
formerbox/contrib/lightning/lightning_trainer.py
formerbox/data/__init__.py
formerbox/data/binarizer.py
formerbox/data/binarizer_default.py
formerbox/data/binarizer_translation.py
formerbox/data/data_collator.py
formerbox/data/dataset_converter.py
formerbox/data/dataset_iterators.py
formerbox/data/indexed_dataset.py
formerbox/data/indexed_dataset_setup.py
formerbox/data/mmap_dataset.py
formerbox/data/samplers/__init__.py
formerbox/data/samplers/batch_sampler.py
formerbox/data/samplers/distributed_batch_sampler.py
formerbox/data/samplers/uniform_batch_sampler.py
formerbox/data/tokenizers/__init__.py
formerbox/data/tokenizers/tokenization_bart.py
formerbox/data/tokenizers/tokenization_bart_trainer.py
formerbox/data/tokenizers/tokenization_base.py
formerbox/data/tokenizers/tokenization_gpt2.py
formerbox/data/tokenizers/tokenization_gpt2_trainer.py
formerbox/data/tokenizers/tokenization_roberta.py
formerbox/data/tokenizers/tokenization_roberta_trainer.py
formerbox/data/tokenizers/tokenization_trainer.py
formerbox/data/translation_dataset.py
formerbox/models/__init__.py
formerbox/modules/__init__.py
formerbox/modules/callbacks/__init__.py
formerbox/modules/callbacks/save_step_checkpoint.py
formerbox/modules/denoising_datamodule.py
formerbox/modules/denoising_module.py
formerbox/modules/lightning_module_mixin.py
formerbox/modules/masked_lm_datamodule.py
formerbox-0.2.0.dist-info/entry_points.txt
formerbox-0.2.0.dist-info/LICENSE
formerbox-0.2.0.dist-info/WHEEL
formerbox-0.2.0.dist-info/METADATA
formerbox-0.2.0.dist-info/RECORD
