Metadata-Version: 2.1
Name: formerbox
Version: 0.2.0
Summary: 
Author: mozharovsky
Author-email: mozharovsky@live.com
Requires-Python: >=3.6.9,<4.0.0
Classifier: Programming Language :: Python :: 3
Classifier: Programming Language :: Python :: 3.7
Classifier: Programming Language :: Python :: 3.8
Classifier: Programming Language :: Python :: 3.9
Requires-Dist: PyYAML (>=5.3.1,<6.0.0)
Requires-Dist: boto3 (>=1.15.11,<2.0.0)
Requires-Dist: dataclasses (>=0.7,<0.8); python_version >= "3.6" and python_version < "3.7"
Requires-Dist: datasets (>=1.2.1,<2.0.0)
Requires-Dist: docutils (>=0.16,<0.17)
Requires-Dist: jsonlines (>=1.2.0,<2.0.0)
Requires-Dist: matplotlib (>=3.2.1,<4.0.0)
Requires-Dist: more-itertools (>=8.5.0,<9.0.0)
Requires-Dist: numpy (>=1.19.5,<2.0.0)
Requires-Dist: overrides (>=3.1.0,<4.0.0)
Requires-Dist: pandas (>=1.1.5,<2.0.0)
Requires-Dist: pydriller (>=1.15.2,<2.0.0)
Requires-Dist: pytorch-lightning (>=1.1.0,<1.2.0)
Requires-Dist: rstcheck (>=3.3.1,<4.0.0)
Requires-Dist: sacrebleu (>=1.4.13,<2.0.0)
Requires-Dist: scikit-learn (>=0.23.1,<0.24.0)
Requires-Dist: scipy (>=1.4.1,<2.0.0)
Requires-Dist: spacy (>=2.2.4,<3.0.0)
Requires-Dist: sphinx (>=3.2.1,<4.0.0)
Requires-Dist: sphinx-autobuild (>=2020.9.1,<2021.0.0)
Requires-Dist: torch (>=1.7.0,<1.8.0)
Requires-Dist: tqdm (>=4.46.1,<5.0.0)
Requires-Dist: traitlets (>=4.3.3,<5.0.0)
Requires-Dist: transformers (>=4.2.1,<5.0.0)
Requires-Dist: tree_sitter (>=0.1.1,<0.2.0)
Requires-Dist: typing_extensions (>=3.7.4,<4.0.0)
Requires-Dist: typing_inspect (>=0.6.0,<0.7.0)
Requires-Dist: wandb (>=0.10.5,<0.11.0)
